setup.py
gaus_and_bin_distributions/Binomialdistribution.py
gaus_and_bin_distributions/Gaussiandistribution.py
gaus_and_bin_distributions/Generaldistribution.py
gaus_and_bin_distributions/__init__.py
gaus_and_bin_distributions.egg-info/PKG-INFO
gaus_and_bin_distributions.egg-info/SOURCES.txt
gaus_and_bin_distributions.egg-info/dependency_links.txt
gaus_and_bin_distributions.egg-info/not-zip-safe
gaus_and_bin_distributions.egg-info/top_level.txt